Flask_Arangodb-1.0.4.dist-info/DESCRIPTION.rst
Flask_Arangodb-1.0.4.dist-info/METADATA
Flask_Arangodb-1.0.4.dist-info/RECORD
Flask_Arangodb-1.0.4.dist-info/WHEEL
Flask_Arangodb-1.0.4.dist-info/metadata.json
Flask_Arangodb-1.0.4.dist-info/top_level.txt
Tests/__init__.py
Tests/test_flask_arangodb.py
flask_arangodb/__init__.py
flask_arangodb/arangodb.py
