Metadata-Version: 2.0
Name: Flask-Arangodb
Version: 1.0.4
Summary: Flask extension for ArangoDB using python-arango
Home-page: https://github.com/sebastiancodes/Flask-Arangodb
Author: Bas van den Broek
Author-email: cwasvandenbroek@gmail.com
License: MIT
Platform: UNKNOWN
Classifier: Development Status :: 3 - Alpha
Classifier: Intended Audience :: Developers
Classifier: Natural Language :: English
Classifier: Environment :: Web Environment
Classifier: Intended Audience :: Developers
Classifier: License :: OSI Approved :: MIT License
Classifier: Operating System :: OS Independent
Classifier: Programming Language :: Python
Classifier: Topic :: Internet :: WWW/HTTP :: Dynamic Content
Classifier: Topic :: Software Development :: Libraries :: Python Modules
Requires-Dist: flask
Requires-Dist: python-arango
Requires-Dist: requests
Requires-Dist: six
